spreadsheetbot/__init__.py
spreadsheetbot/spreadsheetbot.py
spreadsheetbot/basic/__init__.py
spreadsheetbot/basic/drive.py
spreadsheetbot/basic/errors.py
spreadsheetbot/basic/handlers.py
spreadsheetbot/basic/log.py
spreadsheetbot/basic/scheldue.py
spreadsheetbot/sheets/__init__.py
spreadsheetbot/sheets/abstract.py
spreadsheetbot/sheets/groups.py
spreadsheetbot/sheets/i18n.py
spreadsheetbot/sheets/keyboard.py
spreadsheetbot/sheets/log.py
spreadsheetbot/sheets/notifications.py
spreadsheetbot/sheets/registration.py
spreadsheetbot/sheets/replysheet.py
spreadsheetbot/sheets/report.py
spreadsheetbot/sheets/settings.py
spreadsheetbot/sheets/switch.py
spreadsheetbot/sheets/users.py
spreadsheetbot-2.5.1.dist-info/METADATA
spreadsheetbot-2.5.1.dist-info/WHEEL
spreadsheetbot-2.5.1.dist-info/licenses/LICENSE.txt
spreadsheetbot-2.5.1.dist-info/RECORD
