Metadata-Version: 2.1
Name: spreadsheetbot
Version: 2.5.1
Summary: Google Spreadsheet-based Telegram Bot Package
Project-URL: Homepage, https://github.com/twobrowin-study/spreadsheetbot-lib
Project-URL: Bug Tracker, https://github.com/twobrowin-study/spreadsheetbot-lib/issues
Author-email: Egor Dubrovin <dubrovin.en@ya.ru>
License-File: LICENSE.txt
Classifier: License :: OSI Approved :: MIT License
Classifier: Operating System :: OS Independent
Classifier: Programming Language :: Python :: 3
Requires-Python: >=3.11
Requires-Dist: aiohttp
Requires-Dist: filetype
Requires-Dist: gspread
Requires-Dist: gspread-asyncio
Requires-Dist: pandas
Requires-Dist: python-telegram-bot>=20.0b0
Requires-Dist: python-telegram-bot[job-queue]
